verilator/test/sub1.sv
module sub1(
            input logic a,
            input logic b,
            output logic res
            );

   assign res = a & b;

endmodule

verilator/test/test.sv
module test(
            input logic clk,
            input logic  a,
            input logic  b,
            output logic res
            );

   logic res1;

   sub1 mod1 (
              .a(a),
              .b(b),
              .res(res1)
              );

     assign res = ~res1;

endmodule

verilator/test/waveform.vcd
$version Generated by VerilatedVcd $end
$timescale 1ps $end
 $scope module TOP $end
  $var wire 1 # clk $end
  $var wire 1 $ a $end
  $var wire 1 % b $end
  $var wire 1 & res $end
  $scope module test $end
   $var wire 1 # clk $end
   $var wire 1 $ a $end
   $var wire 1 % b $end
   $var wire 1 & res $end
   $var wire 1 ' res1 $end
   $scope module mod1 $end
    $var wire 1 $ a $end
    $var wire 1 % b $end
    $var wire 1 ' res $end
   $upscope $end
  $upscope $end
 $upscope $end
$enddefinitions $end


#0
1#
0$
0%
1&
0'
#1
0#
#2
1#
1$
#3
0#
#4
1#
0$
#5
0#
#6
1#
#7
0#
#8
1#
1%
#9
0#
#10
1#
0%
#11
0#
#12
1#
#13
0#
#14
1#
#15
0#
#16
1#
#17
0#
#18
1#
1$
1%
1'
#19
0#
0&
#20
1#
0$
0%
0'
#21
0#
1&
